README.rst
setup.cfg
setup.py
src/data_conversion_tff/__init__.py
src/data_conversion_tff/main.py
src/data_conversion_tff.egg-info/PKG-INFO
src/data_conversion_tff.egg-info/SOURCES.txt
src/data_conversion_tff.egg-info/dependency_links.txt
src/data_conversion_tff.egg-info/requires.txt
src/data_conversion_tff.egg-info/top_level.txt