Metadata-Version: 2.1
Name: data-conversion-tff
Version: 1.0
Summary: Federated learning library to convert the csv, image or text datasets into federated datasets for clients to run their edge models.
Home-page: https://github.com/divya034/tff_data_converter
Author: Divya Reddy Polaka
Author-email: polakadivya.reddy2019@vitstudent.ac.in
License: UNKNOWN
Platform: UNKNOWN
